optlang_enumerator/__init__.py
optlang_enumerator/cMCS_enumerator.py
optlang_enumerator/cobra_cnapy.py
optlang_enumerator/mcs_computation.py
optlang_enumerator-0.0.13.dist-info/LICENSE
optlang_enumerator-0.0.13.dist-info/METADATA
optlang_enumerator-0.0.13.dist-info/WHEEL
optlang_enumerator-0.0.13.dist-info/top_level.txt
optlang_enumerator-0.0.13.dist-info/RECORD
