Metadata-Version: 2.1
Name: optlang_enumerator
Version: 0.0.13
Summary: Module for enumerating minimal cut sets
Author-email: Axel von Kamp <vonkamp@mpi-magdeburg.mpg.de>
Project-URL: Homepage, https://github.com/cnapy-org/optlang_enumerator
Project-URL: Issues, https://github.com/cnapy-org/optlang_enumerator/issues
Classifier: Programming Language :: Python :: 3
Classifier: License :: OSI Approved :: Apache Software License
Classifier: Operating System :: OS Independent
Requires-Python: >=3.8
License-File: LICENSE
Requires-Dist: numpy ==1.23.*
Requires-Dist: scipy
Requires-Dist: cobra >=0.29
Requires-Dist: optlang
Requires-Dist: efmtool-link >=0.0.6
Requires-Dist: sympy >=1.12
Requires-Dist: swiglpk
